CHANGES.txt
LICENCE.txt
MANIFEST.in
README.rst
setup.cfg
setup.py
django_twitter_tag.egg-info/PKG-INFO
django_twitter_tag.egg-info/SOURCES.txt
django_twitter_tag.egg-info/dependency_links.txt
django_twitter_tag.egg-info/requires.txt
django_twitter_tag.egg-info/top_level.txt
tests/__init__.py
tests/test_functional.py
tests/test_tag.py
tests/utils.py
twitter_tag/__init__.py
twitter_tag/models.py
twitter_tag/test_settings.py
twitter_tag/utils.py
twitter_tag/templatetags/__init__.py
twitter_tag/templatetags/twitter_tag.py