Metadata-Version: 1.0
Name: django-twitter-tag
Version: 1.2
Summary: A django template tag to display user's recent tweets.
Home-page: https://github.com/coagulant/django-twitter-tag
Author: Ilya Baryshev
Author-email: baryshev@gmail.com
License: MIT
Platform: UNKNOWN
Classifier: Development Status :: 4 - Beta
Classifier: Framework :: Django
Classifier: Intended Audience :: Developers
Classifier: License :: OSI Approved :: MIT License
Classifier: Operating System :: OS Independent
Classifier: Programming Language :: Python
Classifier: Programming Language :: Python :: 2.6
Classifier: Programming Language :: Python :: 2.7
Classifier: Programming Language :: Python :: 3.3
